CHANGES
DEBT
LICENSE
MANIFEST.in
README.md
setup.cfg
setup.py
inflector/__init__.py
plumstats.egg-info/PKG-INFO
plumstats.egg-info/SOURCES.txt
plumstats.egg-info/dependency_links.txt
plumstats.egg-info/not-zip-safe
plumstats.egg-info/top_level.txt