Metadata-Version: 1.1
Name: plumstats
Version: 2.0.8
Summary: UNKNOWN
Home-page: https://github.com/ixmatus/inflector
Author: Parnell Springmeyer
Author-email: parnell@digitalmentat.com
License: UNKNOWN
Keywords: inflector text language english
Platform: UNKNOWN
Classifier: Intended Audience :: Developers
Classifier: License :: OSI Approved :: Python Software Foundation License
Classifier: Programming Language :: Python
Classifier: Topic :: Software Development :: Libraries :: Python Modules
